setup.py
relationships/__init__.py
relationships/keys.py
relationships/relationship.py
relationships.egg-info/PKG-INFO
relationships.egg-info/SOURCES.txt
relationships.egg-info/dependency_links.txt
relationships.egg-info/pbr.json
relationships.egg-info/requires.txt
relationships.egg-info/top_level.txt