Metadata-Version: 1.0
Name: relationships
Version: 0.0.2
Summary: redis backed user relationships
Home-page: http://github.com/emre/relationships
Author: Emre Yilmaz
Author-email: hello@emre.sh
License: MIT
Platform: UNKNOWN
